weather_reporter/cli.py
weather_reporter/utils.py
tn_weather_reporter-0.1.1.dist-info/LICENSE
tn_weather_reporter-0.1.1.dist-info/METADATA
tn_weather_reporter-0.1.1.dist-info/WHEEL
tn_weather_reporter-0.1.1.dist-info/entry_points.txt
tn_weather_reporter-0.1.1.dist-info/top_level.txt
tn_weather_reporter-0.1.1.dist-info/RECORD
