Metadata-Version: 2.1
Name: tn-weather-reporter
Version: 0.1.1
Summary: A Python package to get weather reports for any location.
Home-page: https://github.com/thieunguyen5991/tn_weather_reporter
Author: Thieu Nguyen
Author-email: nguyenthieu2102@gmail.com
License: MIT
Platform: UNKNOWN
Classifier: License :: OSI Approved :: MIT License
Classifier: Programming Language :: Python :: 3
Classifier: Programming Language :: Python :: 3.7
Requires-Dist: requests
